{
"salvare":[
 {
   "buonix": 1,
   "buonidimensione": 45,
   "buoninome": "bad boyz",
   "FIELD4": "",
   "FIELD5": "",
   "FIELD6": ""
 },
 {
   "buonix": 2,
   "buonidimensione": 45,
   "buoninome": "bad boyz",
   "FIELD4": "",
   "FIELD5": "",
   "FIELD6": ""
 },
 {
   "buonix": 3,
   "buonidimensione": 45,
   "buoninome": "bad boyz",
   "FIELD4": "",
   "FIELD5": "",
   "FIELD6": ""
 },
 {
   "buonix": 4,
   "buonidimensione": 45,
   "buoninome": "bad boyz",
   "FIELD4": "",
   "FIELD5": "",
   "FIELD6": ""
 },
 {
   "buonix": 5,
   "buonidimensione": 45,
   "buoninome": "bad boyz",
   "FIELD4": "",
   "FIELD5": "",
   "FIELD6": ""
 },
 {
   "buonix": 6,
   "buonidimensione": 45,
   "buoninome": "bad boyz",
   "FIELD4": "",
   "FIELD5": "",
   "FIELD6": ""
 },
 {
   "buonix": 7,
   "buonidimensione": 45,
   "buoninome": "bad boyz",
   "FIELD4": "",
   "FIELD5": "",
   "FIELD6": ""
 },
 {
   "buonix": 8,
   "buonidimensione": 45,
   "buoninome": "bad boyz",
   "FIELD4": "",
   "FIELD5": "",
   "FIELD6": ""
 },
 {
   "buonix": 9,
   "buonidimensione": 45,
   "buoninome": "bad boyz",
   "FIELD4": "",
   "FIELD5": "",
   "FIELD6": ""
 },
 {
   "buonix": 10,
   "buonidimensione": 45,
   "buoninome": "bad boyz",
   "FIELD4": "",
   "FIELD5": "",
   "FIELD6": ""
 },
 {
   "buonix": 11,
   "buonidimensione": 45,
   "buoninome": "bad boyz",
   "FIELD4": "",
   "FIELD5": "",
   "FIELD6": ""
 },
 {
   "buonix": 12,
   "buonidimensione": 45,
   "buoninome": "bad boyz",
   "FIELD4": "",
   "FIELD5": "",
   "FIELD6": ""
 },
 {
   "buonix": 13,
   "buonidimensione": 45,
   "buoninome": "bad boyz",
   "FIELD4": "",
   "FIELD5": "",
   "FIELD6": ""
 },
 {
   "buonix": 14,
   "buonidimensione": 45,
   "buoninome": "bad boyz",
   "FIELD4": "",
   "FIELD5": "",
   "FIELD6": ""
 },
 {
   "buonix": 15,
   "buonidimensione": 45,
   "buoninome": "bad boyz",
   "FIELD4": "",
   "FIELD5": "",
   "FIELD6": ""
 },
 {
   "buonix": 16,
   "buonidimensione": 45,
   "buoninome": "bad boyz",
   "FIELD4": "",
   "FIELD5": "",
   "FIELD6": ""
 },
 {
   "buonix": 17,
   "buonidimensione": 45,
   "buoninome": "bad boyz",
   "FIELD4": "",
   "FIELD5": "",
   "FIELD6": ""
 },
 {
   "buonix": 18,
   "buonidimensione": 45,
   "buoninome": "bad boyz",
   "FIELD4": "",
   "FIELD5": "",
   "FIELD6": ""
 },
 {
   "buonix": 19,
   "buonidimensione": 45,
   "buoninome": "bad boyz",
   "FIELD4": "",
   "FIELD5": "",
   "FIELD6": ""
 },
 {
   "buonix": 20,
   "buonidimensione": 45,
   "buoninome": "bad boyz",
   "FIELD4": "",
   "FIELD5": "",
   "FIELD6": ""
 }
]
}